{
  "schemaVersion": "2.0",
  "diagnostics": [
    {
      "memberId": "I-certification-linear-b1",
      "D1": {
        "status": "NOT_APPLICABLE",
        "arithmeticExplanation": "The member is not a Finding IV welfare-discount member; no discount operator enters its estimate."
      },
      "D2": {
        "status": "NOT_APPLICABLE",
        "arithmeticExplanation": "The member has no Marshallian welfare vector to which distribution weights can apply."
      },
      "D3": {
        "status": "NOT_APPLICABLE",
        "arithmeticExplanation": "The member estimates a complete statutory 30-year path, not an OM tail share."
      },
      "D4": {
        "status": "NOT_APPLICABLE",
        "arithmeticExplanation": "The member contains no private/public Marshallian-surplus numerator-denominator pair."
      },
      "D5": {
        "status": "COMPUTED",
        "concentrationShadowPair": {
          "findingIIIActivationUpper": 10.34566362,
          "memberAdverseBound": 1.09721816
        },
        "arithmetic": "executed concentration-shadow frequency paired with this member adverse bound"
      }
    },
    {
      "memberId": "I-refusal-linear-b2",
      "D1": {
        "status": "NOT_APPLICABLE",
        "arithmeticExplanation": "The member is not a Finding IV welfare-discount member; no discount operator enters its estimate."
      },
      "D2": {
        "status": "NOT_APPLICABLE",
        "arithmeticExplanation": "The member has no Marshallian welfare vector to which distribution weights can apply."
      },
      "D3": {
        "status": "NOT_APPLICABLE",
        "arithmeticExplanation": "The member estimates a complete statutory 30-year path, not an OM tail share."
      },
      "D4": {
        "status": "NOT_APPLICABLE",
        "arithmeticExplanation": "The member contains no private/public Marshallian-surplus numerator-denominator pair."
      },
      "D5": {
        "status": "COMPUTED",
        "concentrationShadowPair": {
          "findingIIIActivationUpper": 10.34566362,
          "memberAdverseBound": 1.09646003
        },
        "arithmetic": "executed concentration-shadow frequency paired with this member adverse bound"
      }
    },
    {
      "memberId": "II-certification-linear-b1",
      "D1": {
        "status": "NOT_APPLICABLE",
        "arithmeticExplanation": "The member is not a Finding IV welfare-discount member; no discount operator enters its estimate."
      },
      "D2": {
        "status": "NOT_APPLICABLE",
        "arithmeticExplanation": "The member has no Marshallian welfare vector to which distribution weights can apply."
      },
      "D3": {
        "status": "NOT_APPLICABLE",
        "arithmeticExplanation": "The member estimates a complete statutory 30-year path, not an OM tail share."
      },
      "D4": {
        "status": "NOT_APPLICABLE",
        "arithmeticExplanation": "The member contains no private/public Marshallian-surplus numerator-denominator pair."
      },
      "D5": {
        "status": "COMPUTED",
        "concentrationShadowPair": {
          "findingIIIActivationUpper": 10.34566362,
          "memberAdverseBound": 102.72839759
        },
        "arithmetic": "executed concentration-shadow frequency paired with this member adverse bound"
      }
    },
    {
      "memberId": "II-refusal-linear-b2",
      "D1": {
        "status": "NOT_APPLICABLE",
        "arithmeticExplanation": "The member is not a Finding IV welfare-discount member; no discount operator enters its estimate."
      },
      "D2": {
        "status": "NOT_APPLICABLE",
        "arithmeticExplanation": "The member has no Marshallian welfare vector to which distribution weights can apply."
      },
      "D3": {
        "status": "NOT_APPLICABLE",
        "arithmeticExplanation": "The member estimates a complete statutory 30-year path, not an OM tail share."
      },
      "D4": {
        "status": "NOT_APPLICABLE",
        "arithmeticExplanation": "The member contains no private/public Marshallian-surplus numerator-denominator pair."
      },
      "D5": {
        "status": "COMPUTED",
        "concentrationShadowPair": {
          "findingIIIActivationUpper": 10.34566362,
          "memberAdverseBound": 102.71989056
        },
        "arithmetic": "executed concentration-shadow frequency paired with this member adverse bound"
      }
    },
    {
      "memberId": "III-certification-linear-b1",
      "D1": {
        "status": "NOT_APPLICABLE",
        "arithmeticExplanation": "The member is not a Finding IV welfare-discount member; no discount operator enters its estimate."
      },
      "D2": {
        "status": "NOT_APPLICABLE",
        "arithmeticExplanation": "The member has no Marshallian welfare vector to which distribution weights can apply."
      },
      "D3": {
        "status": "NOT_APPLICABLE",
        "arithmeticExplanation": "The member estimates a complete statutory 30-year path, not an OM tail share."
      },
      "D4": {
        "status": "NOT_APPLICABLE",
        "arithmeticExplanation": "The member contains no private/public Marshallian-surplus numerator-denominator pair."
      },
      "D5": {
        "status": "COMPUTED",
        "concentrationShadowPair": {
          "findingIIIActivationUpper": 10.34566362,
          "memberAdverseBound": 10.32812254
        },
        "arithmetic": "executed concentration-shadow frequency paired with this member adverse bound"
      }
    },
    {
      "memberId": "III-refusal-linear-b2",
      "D1": {
        "status": "NOT_APPLICABLE",
        "arithmeticExplanation": "The member is not a Finding IV welfare-discount member; no discount operator enters its estimate."
      },
      "D2": {
        "status": "NOT_APPLICABLE",
        "arithmeticExplanation": "The member has no Marshallian welfare vector to which distribution weights can apply."
      },
      "D3": {
        "status": "NOT_APPLICABLE",
        "arithmeticExplanation": "The member estimates a complete statutory 30-year path, not an OM tail share."
      },
      "D4": {
        "status": "NOT_APPLICABLE",
        "arithmeticExplanation": "The member contains no private/public Marshallian-surplus numerator-denominator pair."
      },
      "D5": {
        "status": "COMPUTED",
        "concentrationShadowPair": {
          "findingIIIActivationUpper": 10.34566362,
          "memberAdverseBound": 10.34566362
        },
        "arithmetic": "executed concentration-shadow frequency paired with this member adverse bound"
      }
    },
    {
      "memberId": "IV-certification-linear-b1",
      "D1": {
        "status": "COMPUTED",
        "zeroDiscountOm": 13.4760252,
        "arithmetic": "sum(private marginal value - public counterfactual marginal value), discount factor fixed to one"
      },
      "D2": {
        "status": "COMPUTED",
        "distributionWeightedOm": 9.93557886,
        "baselineConsumption": 66.29838947,
        "arithmetic": "sum(discounted net marginal value × baseline mean canonical consumption / projected canonical consumption), the logarithmic marginal-consumption weight"
      },
      "D3": {
        "status": "COMPUTED",
        "beyondHorizonShare": 0.03415711,
        "numerator": 0.34944096,
        "denominator": 10.23040153,
        "arithmetic": "discounted deposited beyond-horizon value / (absolute controlling OM + discounted beyond-horizon value)"
      },
      "D4": {
        "status": "COMPUTED",
        "publicCaptureNumerator": 16.75704893,
        "privateSurplusDenominator": 30.72902529,
        "arithmetic": "published as the required numerator/denominator pair; no quotient is computed"
      },
      "D5": {
        "status": "COMPUTED",
        "concentrationShadowPair": {
          "findingIIIActivationUpper": 10.34566362,
          "omLowerBound": 9.86406117
        },
        "arithmetic": "paired executed Finding III frequency upper bound and this member OM lower bound"
      }
    },
    {
      "memberId": "IV-refusal-partial-id-b4",
      "D1": {
        "status": "COMPUTED",
        "zeroDiscountOm": 13.4760252,
        "arithmetic": "sum(private marginal value - public counterfactual marginal value), discount factor fixed to one"
      },
      "D2": {
        "status": "COMPUTED",
        "distributionWeightedOm": 9.93557886,
        "baselineConsumption": 66.29838947,
        "arithmetic": "sum(discounted net marginal value × baseline mean canonical consumption / projected canonical consumption), the logarithmic marginal-consumption weight"
      },
      "D3": {
        "status": "COMPUTED",
        "beyondHorizonShare": 0.03415711,
        "numerator": 0.34944096,
        "denominator": 10.23040153,
        "arithmetic": "discounted deposited beyond-horizon value / (absolute controlling OM + discounted beyond-horizon value)"
      },
      "D4": {
        "status": "COMPUTED",
        "publicCaptureNumerator": 16.75704893,
        "privateSurplusDenominator": 30.72902529,
        "arithmetic": "published as the required numerator/denominator pair; no quotient is computed"
      },
      "D5": {
        "status": "COMPUTED",
        "concentrationShadowPair": {
          "findingIIIActivationUpper": 10.34566362,
          "omLowerBound": 9.79201343
        },
        "arithmetic": "paired executed Finding III frequency upper bound and this member OM lower bound"
      }
    }
  ]
}
